sqlcop/__init__.py
sqlcop/cli.py
sqlcop/checks/__init__.py
sqlcop/checks/cross_join.py
sqlcop/checks/order_by_count.py
sqlcop-0.10.18.dist-info/METADATA
sqlcop-0.10.18.dist-info/RECORD
sqlcop-0.10.18.dist-info/WHEEL
sqlcop-0.10.18.dist-info/entry_points.txt
sqlcop-0.10.18.dist-info/top_level.txt
