Metadata-Version: 2.1
Name: sqlcop
Version: 0.10.18
Summary: A cli tool to check and guard against anti-patterns
Home-page: https://github.com/freshbooks/sqlcop
Author: Kevin Qiu
Author-email: kevin@freshbooks.com
License: BSD
Keywords: sqlcop
Platform: UNKNOWN
Classifier: Development Status :: 2 - Pre-Alpha
Classifier: Intended Audience :: Developers
Classifier: License :: OSI Approved :: BSD License
Classifier: Natural Language :: English
Classifier: Programming Language :: Python :: 2.7
Classifier: Programming Language :: Python :: 3
Classifier: Programming Language :: Python :: 3.6
Requires-Dist: sqlparse (==0.2.4)
Requires-Dist: memoized-property (==1.0.3)
Requires-Dist: future
